Workbook

Sheet 填写指南
A1: 基于数据标签挖掘的企业登记注册合规风险监测 — 七列规则表
A3: ■ 这张表是什么
A4: 全项目最硬的资产。它是唯一一个别人抄不走、且能证明团队真读了法规的东西。
A5: 这条链正着读是设计，倒着读是解释。系统报警时复核人员只问一句“凭什么”，
A6: 答案必须是：“因为《XX条例》第X条要求Y，该企业字段Z违反了，故命中标签W。”
A7: 这句话就是前四列倒着念。
A9: ■ 只填「规则表」这一张 sheet 的 C~L 列
A10: A 列（规则ID）和 B 列（分类）已锁定，不要改，改了「配额与进度」的统计会失效。
A11: 第 2 行是示例行（黄色底），格式看懂后请删除整行。
A12: 绿色底 = 法条已核实，可直接用。橙色底 = 待你核实或填写。
A14: ■ 七列的含义与填写要求
A15: C 法条锚点｜必须精确到「条」，最好到「款」。格式：《市场主体登记管理条例》第15条
... A49: 规则类型：法定强制 ｜ 触发时点：事前拦截 ｜ 处置级别：硬阻断

Sheet 规则表
A1: 规则ID | B1: 分类 | C1: 法条锚点 | D1: 字段 | E1: 判定逻辑 | F1: 风险标签 | G1: 规则类型 | H1: 触发时点 | I1: 处置级别 | J1: 状态 | K1: 负责人 | L1: 核查提示 / 备注
A2: 示例 | B2: （示例·请删除本行） | C2: 《公司法》第47条 | D2: 股东认缴出资额, 注册资本 | E2: SUM(股东.认缴出资额) <> 企业.注册资本 | F2: 出资与注册资本不符 | G2: 法定强制 | H2: 事前拦截 | I2: 硬阻断 | J2: 已核 | K2: B | L2: 图约束 C1；有限责任公司适用
A3: R-SM-01 | B3: 实名与身份 | C3: 《市场主体登记管理条例》第15条 | D3: 法定代表人证件类型, 证件号, 姓名 | E3: 实名核验接口返回 <> 通过 | F3: 实名核验不通过 | G3: 法定强制 | H3: 事前拦截 | I3: 硬阻断 | J3: 已核 | K3: B | L3: 条例第15条：市场主体实行实名登记，申请人应当配合登记机关核验身份信息
A4: R-SM-02 | B4: 实名与身份 | C4: 《市场主体登记管理条例实施细则》第16条 | D4: 股东/发起人证件信息 | E4: EXISTS(股东 WHERE 实名核验 <> 通过) | F4: 股东实名核验不通过 | G4: 法定强制 | H4: 事前拦截 | I4: 硬阻断 | J4: 已核 | K4: B | L4: 细则第16条廓清实名登记范围；须确认范围覆盖哪些角色
A5: R-SM-03 | B5: 实名与身份 | C5: 《经营主体登记申请及代理行为管理办法》第13条 | D5: 代理人ID, 备案状态 | E5: 代理人.备案状态 <> 已备案 OR 核验接口 <> 通过 | F5: 代理人未备案 | G5: 法定强制 | H5: 事前拦截 | I5: 硬阻断 | J5: 已核 | K5: B | L5: 2025-10-30起：校验不通过的不得代理申报。★原文须从市场监管法规数据库获取，勿用地方转发解读
A6: R-SM-04 | B6: 实名与身份 | C6: 《经营主体登记申请及代理行为管理办法》第12条 | D6: 代理人ID, 联络员ID, 投资关系 | E6: 同一自然人 = 代理人 AND = 联络员 AND NOT 自行出资设立 | F6: 代理人兼任联络员 | G6: 法定强制 | H6: 事中 | I6: 人工复核 | J6: 已核 | K6: A | L6: 图约束 C6。规定原文：限制登记代理人兼任登记联络员（自行出资设立的除外）
A7: R-SM-05 | B7: 实名与身份 | C7: 《经营主体登记申请及代理行为管理办法》34-36条 | D7: 代理人ID, 30日代办量, 核准率 | E7: 代办量 > 3σ AND 核准率 < 阈值 | F7: 代办行为异常 | G7: 统计异常 | H7: 事后回溯 | I7: 人工复核 | J7: 已核 | K7: A | L7: 阈值须由数据分位数确定，不可拍脑袋；须报告稳定性
A8: R-SM-06 | B8: 实名与身份 | C8: 《公司法》第178条（任职资格）+ 失信名单 | D8: 法定代表人证件号, 失信状态, 任职生效日 | E8: 失信被执行人 AND 任职生效日 IN 失信期 | F8: 失信人员违规任职 | G8: 法定强制 | H8: 事前拦截 | I8: 硬阻断 | J8: 已核 | K8: A | L8: 图约束 C2。★跨省杀手锏：单省数据看不出，全国图谱才暴露。须核实《公司法》任职资格具体条款
A9: R-SM-07 | B9: 实名与身份 | C9: 《经营主体登记申请及代理行为管理办法》第三十二条 | D9: 自然人ID, 任职企业数, 省份分布 | E9: 跨省份数 >= 3 AND 任职企业数 >= N | F9: 职业法人嫌疑 | G9: 统计异常 | H9: 事后回溯 | I9: 人工复核 | J9: 已核 | K9: A | L9: N 与省份数阈值须由分位数确定
A10: R-SM-08 | B10: 实名与身份 | C10: 《经营主体登记申请及代理行为管理办法》第三十二条 | D10: 自然人ID, 任职企业, 证件签发地 | E10: （待设计：官方点名「被法人」的识别口径） | F10: 冒名登记嫌疑 | G10: 情报线索 | H10: 事后回溯 | I10: 人工复核 | J10: 已核 | K10: B | L10: 官方点名的虚假登记类型之一。可参考《撤销冒名登记》相关规定确定口径
A11: R-CZ-01 | B11: 出资与注册资本 | C11: 《公司法》第47条 | D11: 股东认缴出资额, 注册资本 | E11: SUM(股东.认缴出资额) <> 企业.注册资本 | F11: 出资与注册资本不符 | G11: 法定强制 | H11: 事前拦截 | I11: 硬阻断 | J11: 已核 | K11: B | L11: 图约束 C1。第47条：注册资本为全体股东认缴的出资额
A12: R-CZ-02 | B12: 出资与注册资本 | C12: 《公司法》第47条 | D12: 出资缴付期限, 成立日期 | E12: 缴付期限 > 成立日期 + 5年 | F12: 出资期限超五年 | G12: 法定强制 | H12: 事前拦截 | I12: 硬阻断 | J12: 已核 | K12: B | L12: 第47条：自公司成立之日起五年内缴足。注意「法律行政法规另有规定的从其规定」的例外
... A21: R-MC-03 | B21: 名称 | C21: 《企业名称登记管理规定》第12条 | D21: 名称 | E21: 名称含国字头特征词 AND 无相应核准 | F21: 假国企/国字头嫌疑 | G21: 法定强制 | H21: 事前拦截 | I21: 人工复核 | J21: 已核 | K21: B | L21: 官方点名的虚假登记类型：假国企。须核实名称禁限用具体条款
A22: R-MC-04 | B22: 名称 | C22: 《企业名称登记管理规定实施办法》第19条 | D22: 名称, 行政区划, 行业表述 | E22: 名称近似度 > 阈值（同区划同行业） | F22: 名称近似冲突 | G22: 规范性 | H22: 事前拦截 | I22: 人工复核 | J22: 已核 | K22: B
A23: R-MC-05 | B23: 名称 | C23: 《企业名称登记管理规定》第11条 | D23: 名称 | E23: 名称含事业单位特征词 | F23: 假事业单位嫌疑 | G23: 情报线索 | H23: 事后回溯 | I23: 人工复核 | J23: 已核 | K23: B | L23: 官方点名类型
A24: R-MC-06 | B24: 名称 | C24: 《企业名称登记管理规定》第16条 | D24: 名称 | E24: 名称含协会/学会 AND 国字头 | F24: 国字头协会学会嫌疑 | G24: 情报线索 | H24: 事后回溯 | I24: 人工复核 | J24: 已核 | K24: B | L24: 官方点名类型
A25: R-MC-07 | B25: 名称 | C25: 《组织机构统一社会信用代码管理办法》第6条 | D25: 名称, 统一社会信用代码 | E25: 一致性校验服务返回不一致 | F25: 名称代码不一致 | G25: 规范性 | H25: 事中 | I25: 人工复核 | J25: 已核 | K25: A | L25: 总局登记注册局/网数中心/代码中心联合印发。★注意：依据是总局通知而非法律法规，故规则类型为「规范性」不是「法定强制」—— 这一条是自查公式抓出来的典型错误
A26: R-JY-01 | B26: 经营范围与许可 | C26: 《市场主体登记管理条例》第14条 | D26: 经营范围条目, 批准文件 | E26: EXISTS(条目.许可项 = true) AND 批准文件 IS NULL | F26: 许可项无批准文件 | G26: 法定强制 | H26: 事前拦截 | I26: 硬阻断 | J26: 已核 | K26: B | L26: 第14条：登记前依法须经批准的许可经营项目，应当在申请登记时提交有关批准文件
A27: R-JY-02 | B27: 经营范围与许可 | C27: 《市场主体登记管理条例》第14条 | D27: 经营范围条目, 许可证节点 | E27: 含许可项 AND NOT EXISTS(有效许可证) | F27: 许可缺失 | G27: 法定强制 | H27: 事中 | I27: 人工复核 | J27: 已核 | K27: A | L27: 图约束 C3
A28: R-JY-03 | B28: 经营范围与许可 | C28: 《市场主体登记管理条例》第14条 + 《经营范围规范表述目录(试行)》 | D28: 经营范围条目 | E28: 条目 NOT IN 规范表述目录 | F28: 表述不规范 | G28: 规范性 | H28: 事中 | I28: 仅打标 | J28: 已核 | K28: A | L28: ★命中后自动生成「目录缺口建议」→ 这是方案第一创新点的落点。第14条：应当按照登记机关公布的经营项目分类标准办理
A29: R-JY-04 | B29: 经营范围与许可 | C29: 《特种设备生产和充装单位许可规则》(TSG 07—2019) + 《特种设备安全法》第18条 | D29: 经营范围行业码, 特种设备生产许可 | E29: 行业码 IN 特种设备生产码表 AND NOT EXISTS(许可) | F29: 特种设备无证经营 | G29: 法定强制 | H29: 事中 | I29: 硬阻断 | J29: 已核 | K29: A | L29: 图约束 C7。微观专题一
A30: R-JY-05 | B30: 经营范围与许可 | C30: 《特种设备检验机构核准规则》(TSG Z7001-2021) / 《特种设备检测机构核准规则》(TSG Z7002—2022) | D30: 经营范围行业码, 检验检测机构核准 | E30: 行业码 IN 特种设备检验检测码表 AND NOT EXISTS(核准证) | F30: 检验机构未核准 | G30: 法定强制 | H30: 事中 | I30: 硬阻断 | J30: 已核 | K30: A | L30: 微观专题一
A31: R-JY-06 | B31: 经营范围与许可 | C31: 《市场主体登记管理条例》第14条 + 第26条 | D31: 许可证有效期, 经营范围 | E31: 许可证有效期 < 当前日期 AND 经营范围包含许可经营项目 | F31: 许可过期无证经营 | G31: 法定强制 | H31: 事后回溯 | I31: 硬阻断 | J31: 已核 | K31: A
A32: R-JY-07 | B32: 经营范围与许可 | C32: 无（专题标记，非违规） | D32: 经营范围条目 | E32: 经营范围关键词 CONTAINS '网络直播' OR 经营范围关键词 CONTAINS '网络文化经营' | F32: 直播电商专题标记 | G32: 规范性 | H32: 事中 | I32: 仅打标 | J32: 已核 | K32: A | L32: ★微观专题二入口。这不是风险标签，是专题范围标记，G列不可填法定强制
A33: R-JY-08 | B33: 经营范围与许可 | C33: 《市场监管总局办公厅关于提升信息化水平统一规范市场主体登记注册工作的通知》（市监注〔2020〕85号） | D33: 经营范围行业码，许可审批部门，双告知推送状态 | E33: 经营范围行业码 IN 后置许可目录 AND 双告知推送状态 = ‘未推送’ | F33: 双告知未推送 | G33: 规范性 | H33: 事中 | I33: 仅打标 | J33: 已核 | K33: C | L33: 通知要求：实现「双告知」的自动化、智能化推送。挂载对象是业务单据不是企业
A34: R-ZS-01 | B34: 住所 | C34: 《公司法》第32条 | D34: 住所 | E34: 住所 IS NULL OR 住所 = '' | F34: 住所缺失 | G34: 法定强制 | H34: 事前拦截 | I34: 硬阻断 | J34: 已核 | K34: B | L34: 第32条：住所为公司登记事项
A35: R-ZS-02 | B35: 住所 | C35: 《市场主体登记管理条例》第17条、第40条（虚假登记推定） | D35: 标准地址ID, 同址主体数 | E35: 同址主体数 > 全省 P99 | F35: 住所高度聚集 | G35: 统计异常 | H35: 事后回溯 | I35: 人工复核 | J35: 已核 | K35: A | L35: ★C列无法条，G列必须是统计异常。依赖地址标准化到门牌粒度，否则全部失效
A36: R-ZS-03 | B36: 住所 | C36: 《市场主体登记管理条例》第17条、第40条（虚假登记推定） | D36: 标准地址ID, 30日新增主体数 | E36: 30日新增 > 阈值 | F36: 住所批量注册 | G36: 统计异常 | H36: 事后回溯 | I36: 人工复核 | J36: 已核 | K36: A | L36: 阈值由分位数确定
A37: R-ZS-04 | B37: 住所 | C37: 《市场主体登记管理条例》第11条、第17条 | D37: 住所文本 | E37: 地址标准化失败 OR 无法解析到门牌 | F37: 地址不可解析 | G37: 规范性 | H37: 事中 | I37: 仅打标 | J37: 已核 | K37: B | L37: ★这条同时是数据质量指标，挂载对象是业务单据。地址归一准确率须单独评测
A38: R-ZS-05 | B38: 住所 | C38: （属地政策，各省不同） | D38: 地址性质, 集群注册备案 | E38: 集群注册地址 AND 未按属地要求备案 | F38: 集群注册未备案 | G38: 规范性 | H38: 事后回溯 | I38: 仅打标 | J38: 已核 | K38: B | L38: ★典型的「属地差异化参数」案例，可用于论证「统一规则中台+属地参数」的设计
A39: R-BG-01 | B39: 变更与备案 | C39: 《市场主体登记管理条例》第24条 | D39: 变更决议日期, 变更申请日期 | E39: 申请日期 - 决议日期 > 30日 | F39: 变更登记逾期 | G39: 法定强制 | H39: 事后回溯 | I39: 仅打标 | J39: 已核 | K39: B | L39: 第24条：自作出变更决议、决定或者法定变更事项发生之日起30日内申请变更登记
A40: R-BG-02 | B40: 变更与备案 | C40: 《市场主体登记管理条例》第24条 | D40: 变更事项, 批准文件有效期, 申请日期 | E40: 须批准的变更 AND 申请日期 NOT IN 批准文件有效期 | F40: 批准文件过期 | G40: 法定强制 | H40: 事中 | I40: 人工复核 | J40: 已核 | K40: B | L40: 第24条：属于依法须经批准的，应当在批准文件有效期内申请变更登记
A41: R-BG-03 | B41: 变更与备案 | C41: 《市场主体登记管理条例》第9条 | D41: 章程, 经营期限, 出资信息, 董监高, 登记联络员, 受益所有人 | E41: 任一法定备案事项缺失 | F41: 备案事项不全 | G41: 法定强制 | H41: 事中 | I41: 仅打标 | J41: 已核 | K41: B | L41: 第9条完整列举备案事项
A42: R-BG-04 | B42: 变更与备案 | C42: 《受益所有人信息管理办法》第2条 + 《条例》第9条 | D42: 受益所有人信息 | E42: 应备案 AND 未备案 | F42: 受益所有人未备案 | G42: 法定强制 | H42: 事中 | I42: 人工复核 | J42: 已核 | K42: A | L42: 办法第2条：公司应当通过相关登记注册系统备案受益所有人信息。是股权穿透的法源
A43: R-BG-05 | B43: 变更与备案 | C43: 《公司法》第141条（针对上市公司） / 《受益所有人信息管理办法》第2条、第6条、第10条 | D43: 投资关系图谱 | E43: EXISTS 有向环 (e)-[:投资*1..6]->(e) | F43: 股权自环 | G43: 法定强制 | H43: 事后回溯 | I43: 人工复核 | J43: 已核 | K43: A | L43: 图约束 C5。★法条依据须核实；若核实不到，G列改为「统计异常」或「情报线索」
... A52: R-XN-04 | B52: 效能与数据质量 | C52: 《市场主体登记数据质量建设实施方案》及相关数据质量评价标准 | D52: 各质量维度字段, 登记机关ID | E52: 按总局质量评价标准计算的省级得分＜阈值 | F52: 数据质量得分低 | G52: 规范性 | H52: 事后回溯 | I52: 仅打标 | J52: 已核 | K52: B | L52: ★★该标准原文是本项目最重要的待获取文件。它定义了总局怎么评价数据质量，直接决定宏观层指标口径

Sheet 配额与进度
A1: 分类 | B1: 配额 | C1: 已核 | D1: 待核 | E1: 待填 | F1: 完成率 | G1: 主要法源
A2: 实名与身份 | B2: 8 | C2: =COUNTIFS(规则表!$B$3:$B$52,$A2,规则表!$J$3:$J$52,"已核") | D2: =COUNTIFS(规则表!$B$3:$B$52,$A2,规则表!$J$3:$J$52,"待核") | E2: =COUNTIFS(规则表!$B$3:$B$52,$A2,规则表!$J$3:$J$52,"待填") | F2: =IFERROR(C2/B2,0) | G2: 《条例》第15条、《实施细则》第16条、《经营主体登记申请及代理行为管理办法》
A3: 出资与注册资本 | B3: 8 | C3: =COUNTIFS(规则表!$B$3:$B$52,$A3,规则表!$J$3:$J$52,"已核") | D3: =COUNTIFS(规则表!$B$3:$B$52,$A3,规则表!$J$3:$J$52,"待核") | E3: =COUNTIFS(规则表!$B$3:$B$52,$A3,规则表!$J$3:$J$52,"待填") | F3: =IFERROR(C3/B3,0) | G3: 《公司法》第47/96条、国发〔2014〕7号、《条例》第9条
A4: 名称 | B4: 7 | C4: =COUNTIFS(规则表!$B$3:$B$52,$A4,规则表!$J$3:$J$52,"已核") | D4: =COUNTIFS(规则表!$B$3:$B$52,$A4,规则表!$J$3:$J$52,"待核") | E4: =COUNTIFS(规则表!$B$3:$B$52,$A4,规则表!$J$3:$J$52,"待填") | F4: =IFERROR(C4/B4,0) | G4: 《企业名称登记管理规定》及实施办法、《公司法》第32条、2026年版文书规范
A5: 经营范围与许可 | B5: 8 | C5: =COUNTIFS(规则表!$B$3:$B$52,$A5,规则表!$J$3:$J$52,"已核") | D5: =COUNTIFS(规则表!$B$3:$B$52,$A5,规则表!$J$3:$J$52,"待核") | E5: =COUNTIFS(规则表!$B$3:$B$52,$A5,规则表!$J$3:$J$52,"待填") | F5: =IFERROR(C5/B5,0) | G5: 《条例》第14条、《经营范围规范表述目录》、TSG 07—2019 / Z7001 / Z7002
A6: 住所 | B6: 5 | C6: =COUNTIFS(规则表!$B$3:$B$52,$A6,规则表!$J$3:$J$52,"已核") | D6: =COUNTIFS(规则表!$B$3:$B$52,$A6,规则表!$J$3:$J$52,"待核") | E6: =COUNTIFS(规则表!$B$3:$B$52,$A6,规则表!$J$3:$J$52,"待填") | F6: =IFERROR(C6/B6,0) | G6: 《公司法》第32条、《市场主体准入退出数据规范》、属地集群注册政策
A7: 变更与备案 | B7: 6 | C7: =COUNTIFS(规则表!$B$3:$B$52,$A7,规则表!$J$3:$J$52,"已核") | D7: =COUNTIFS(规则表!$B$3:$B$52,$A7,规则表!$J$3:$J$52,"待核") | E7: =COUNTIFS(规则表!$B$3:$B$52,$A7,规则表!$J$3:$J$52,"待填") | F7: =IFERROR(C7/B7,0) | G7: 《条例》第9/24条、《受益所有人信息管理办法》第2条
A8: 退出与注销 | B8: 4 | C8: =COUNTIFS(规则表!$B$3:$B$52,$A8,规则表!$J$3:$J$52,"已核") | D8: =COUNTIFS(规则表!$B$3:$B$52,$A8,规则表!$J$3:$J$52,"待核") | E8: =COUNTIFS(规则表!$B$3:$B$52,$A8,规则表!$J$3:$J$52,"待填") | F8: =IFERROR(C8/B8,0) | G8: 《公司法》第37/239/240条、《企业注销指引(2023年修订)》
A9: 效能与数据质量 | B9: 4 | C9: =COUNTIFS(规则表!$B$3:$B$52,$A9,规则表!$J$3:$J$52,"已核") | D9: =COUNTIFS(规则表!$B$3:$B$52,$A9,规则表!$J$3:$J$52,"待核") | E9: =COUNTIFS(规则表!$B$3:$B$52,$A9,规则表!$J$3:$J$52,"待填") | F9: =IFERROR(C9/B9,0) | G9: 《提升信息化水平统一规范市场主体登记注册工作的通知》、《市场主体登记数据质量建设实施方案》
A10: 合计 | B10: =SUM(B2:B9) | C10: =SUM(C2:C9) | D10: =SUM(D2:D9) | E10: =SUM(E2:E9) | F10: =IFERROR(C10/B10,0)
A12: ■ 一致性自查（做完必须全为 0）
A13: 无法条却标法定强制的行数： | B13: =COUNTIFS(规则表!$C$3:$C$52,"",规则表!$G$3:$G$52,"法定强制")+COUNTIFS(规则表!$C$3:$C$52,"无*",规则表!$G$3:$G$52,"法定强制")
A14: 硬阻断却非法定强制的行数： | B14: =COUNTIFS(规则表!$I$3:$I$52,"硬阻断")-COUNTIFS(规则表!$I$3:$I$52,"硬阻断",规则表!$G$3:$G$52,"法定强制")
A16: 上面两个数字任一 > 0，说明规则表有逻辑错误，会在答辩现场被戳穿。
A18: ■ 配额说明
A19: 配额按第一梯队法规的结构分配，不是拍脑袋。若某类实际写出的规则超过配额，不必强行删除 ——
A20: 配额是下限提示，用于防止漏掉整个类别（最常见的漏项是「效能与数据质量」，因为所有人都只想着给企业打标签）。

Sheet 参考来源
A1: 法规 / 文件 | B1: 链接 | C1: 备注
A2: 《市场主体登记管理条例》 | B2: https://flk.npc.gov.cn/detail2.html?ZmY4MDgxODE3YjYzYjY3OTAxN2I3YjIwODU5NTM2MDc | C2: 第9条备案事项、第14条经营范围、第15条实名登记、第24条变更登记
A3: 《市场主体登记管理条例实施细则》 | B3: https://www.gov.cn/gongbao/content/2022/content_5688790.htm | C3: 第16条实名登记范围
A4: 《中华人民共和国公司法》 | B4: http://www.npc.gov.cn/c2/c30834/202312/t20231229_433999.html | C4: 第32条登记事项、第47条注册资本五年缴足、第96条股份公司、第37/239/240条注销
A5: 《企业名称登记管理规定》 | B5: https://www.gov.cn/gongbao/content/2021/content_5582625.htm | C5: 名称禁限用条款待核
A6: 《企业名称登记管理规定实施办法》 | B6: https://www.gov.cn/gongbao/2023/issue_10806/202311/content_6913825.html | C6: 名称近似判断待核
A7: 《国务院关于印发注册资本登记制度改革方案的通知》(国发〔2014〕7号) | B7: https://www.gov.cn/gongbao/content/2014/content_2620280.htm | C7: 实缴制行业名录
A8: 《受益所有人信息管理办法》 | B8: http://www.pbc.gov.cn/tiaofasi/144941/144957/5342579/index.html | C8: 第2条备案义务
A9: 《企业信息公示暂行条例》 | B9: https://www.gov.cn/gongbao/content/2014/content_2745920.htm | C9: 第8条年报期限、第9条年报内容
A10: 《企业注销指引(2023年修订)》 | B10: https://www.samr.gov.cn/zw/zfxxgk/fdzdgknr/djzcj/art/2023/art_1cda5f346be248e799a3454a93821aa3.html | C10: 普通/简易注销流程
A11: 《经营主体登记文书规范/提交材料规范(2026年版)》(国市监注发〔2026〕5号) | B11: https://www.samr.gov.cn/zw/zfxxgk/fdzdgknr/djzcj/art/2026/art_3321d681741f48cfa3a8e6ef4b15cccd.html | C11: 2026-05-01施行，替代2022年版。禁用词新规须在此核实
A12: 《关于推进企业信用风险分类管理的意见》 | B12: https://www.samr.gov.cn/xyjgs/gzdt/art/2023/art_470789abe07f43b9bc249070c2f424ce.html | C12: A/B/C/D四类；「不是对企业的信用评价」
... A18: 国家企业信用信息公示系统 | B18: https://www.gsxt.gov.cn/index.html | C18: 真实数据采集源
A21: ■ 尚未获取到官方原文，须优先补齐（按重要性）
A22: 《市场主体登记数据质量建设实施方案》及数据质量评价标准 | B22: ★★★ 最重要。它定义总局怎么评价数据质量，直接决定宏观层全部指标口径
A23: 《经营主体登记申请及代理行为管理办法》(2025) | B23: ★★★ 代理人核验的法源。目前只找到各地转发的解读，须找原文
A24: 《经营范围规范表述目录(试行)》 | B24: ★★★ R-JY-03 与「目录缺口建议」的基础数据
A25: 《市场主体准入退出数据规范》 | B25: ★★ 字段口径的标准
A26: 2026年版禁用词完整清单（虚拟货币/稳定币/RWA等） | B26: ★★ R-MC-02 的词表；最佳Demo素材
